[{"tid": "20:00", "dato": "2021-03-16", "kampID": "46d5de28-3f8e-4bc7-b487-d6b2d57d4c3f", "lag1ID": "4d514a66-def6-4d7b-8974-7eb310b83a9d", "lag2ID": "997cb342-c0d4-4b1c-960b-1dad3b9b6393", "antallKamper": 2, "divisjon": "1. Divisjon", "liga": "Telialigaen", "spill": "League of Legends", "lag2": {"navn": "Bifrost", "kallenavn": "Bifrost", "spill": "League of Legends", "tag": "BFR", "bilde": "Bifrost_logo.png", "id": "997cb342-c0d4-4b1c-960b-1dad3b9b6393", "gamernoID": "132253", "obsninja": {"link": "", "brukernavn": "", "passord": ""}, "spillere": [{"navn": "I am Kees", "id": "78115", "rolle": "top", "spillerBilde": "https://img.gfx.no/1539/1539009/no-image.160x160c.png", "ingameNavn": "Naerea", "bilde": "Roshan_Drawing.png"}, {"navn": "Tanu", "id": "106360", "rolle": "jgl", "spillerBilde": "https://img.gfx.no/1539/1539009/no-image.160x160c.png", "ingameNavn": "Tanu", "bilde": "Tanu_Drawing.png"}, {"navn": "HHNeverLucky", "id": "56074", "rolle": "mid", "spillerBilde": "https://img.gfx.no/2461/2461741/04f2c811e29bd8d89881d24eb0dca1aa.160x160c.png", "ingameNavn": "HHNeverLucky v2", "bilde": "HawHaw_Drawing.png"}, {"navn": "Tidebringer", "id": "27789", "rolle": "adc", "spillerBilde": "https://img.gfx.no/2391/2391091/original.160x160c.jpg", "ingameNavn": "Tidebringer", "bilde": "Tide_Drawing.png"}, {"navn": "Bruland", "id": "83066", "rolle": "sup", "spillerBilde": "https://img.gfx.no/2607/2607472/cfa00701-269e-482e-a26c-198a2941595e.160x160c.jpg", "ingameNavn": "BruIand", "bilde": "Bruland_Drawing.png"}, {"navn": "", "id": "", "rolle": "chc", "spillerBilde": "", "ingameNavn": "", "bilde": ""}]}, "lag1": {"navn": "Vanir", "kallenavn": "Vanir", "spill": "League of Legends", "tag": "VNR", "bilde": "Vanir_logo.png", "id": "4d514a66-def6-4d7b-8974-7eb310b83a9d", "gamernoID": "119522", "spillere": [{"navn": "Flair", "id": "108263", "rolle": "top", "spillerBilde": "https://img.gfx.no/1539/1539009/no-image.160x160c.png", "ingameNavn": "VNR Flair"}, {"navn": "Metanon", "id": "67549", "rolle": "jgl", "spillerBilde": "https://img.gfx.no/2462/2462973/portrett.160x160c.jpg", "ingameNavn": "VNR Metanon"}, {"navn": "coing", "id": "106507", "rolle": "mid", "spillerBilde": "https://img.gfx.no/2644/2644680/78090505-2529728490445572-3929645009959124992-n.160x160c.jpg", "ingameNavn": "VNR coing"}, {"navn": "Riziki", "id": "57914", "rolle": "adc", "spillerBilde": "https://img.gfx.no/2645/2645695/ohep3jbv-400x400.160x160c.jpg", "ingameNavn": "VNR Riziki"}, {"navn": "Blazingfire", "id": "47252", "rolle": "sup", "spillerBilde": "https://img.gfx.no/2463/2463683/lemur.160x160c.jpg", "ingameNavn": "VNR BlazingFire"}, {"navn": "", "id": "", "rolle": "chc", "spillerBilde": "", "ingameNavn": ""}]}}, {"tid": "18:00", "dato": "2021-03-18", "kampID": "f052a541-d06f-48fa-a867-2057af31c10c", "lag1ID": "fb96e741-368d-41ad-ab0b-12684d8b2bcc", "lag2ID": "4d514a66-def6-4d7b-8974-7eb310b83a9d", "antallKamper": 2, "divisjon": "1. Divisjon", "liga": "Telialigaen", "spill": "League of Legends", "lag2": {"navn": "Vanir", "kallenavn": "Vanir", "spill": "League of Legends", "tag": "VNR", "bilde": "Vanir_logo.png", "id": "4d514a66-def6-4d7b-8974-7eb310b83a9d", "gamernoID": "119522", "spillere": [{"navn": "Flair", "id": "108263", "rolle": "top", "spillerBilde": "https://img.gfx.no/1539/1539009/no-image.160x160c.png", "ingameNavn": "VNR Flair"}, {"navn": "Metanon", "id": "67549", "rolle": "jgl", "spillerBilde": "https://img.gfx.no/2462/2462973/portrett.160x160c.jpg", "ingameNavn": "VNR Metanon"}, {"navn": "coing", "id": "106507", "rolle": "mid", "spillerBilde": "https://img.gfx.no/2644/2644680/78090505-2529728490445572-3929645009959124992-n.160x160c.jpg", "ingameNavn": "VNR coing"}, {"navn": "Riziki", "id": "57914", "rolle": "adc", "spillerBilde": "https://img.gfx.no/2645/2645695/ohep3jbv-400x400.160x160c.jpg", "ingameNavn": "VNR Riziki"}, {"navn": "Blazingfire", "id": "47252", "rolle": "sup", "spillerBilde": "https://img.gfx.no/2463/2463683/lemur.160x160c.jpg", "ingameNavn": "VNR BlazingFire"}, {"navn": "", "id": "", "rolle": "chc", "spillerBilde": "", "ingameNavn": ""}]}, "lag1": {"navn": "Nordavind DNB", "kallenavn": "NVD-MAIN", "spill": "League of Legends", "tag": "NVD", "bilde": "Nordavind_logo.png", "id": "fb96e741-368d-41ad-ab0b-12684d8b2bcc", "gamernoID": "37826", "spillere": [{"navn": "Kerberos", "id": "106747", "rolle": "top", "spillerBilde": "https://img.gfx.no/2642/2642013/dbl-kerberos-2019-split-1.160x160c.png", "ingameNavn": "kerberos 2"}, {"navn": "Sharptho", "id": "42162", "rolle": "jgl", "spillerBilde": "https://img.gfx.no/2602/2602085/portrettbilde.160x160c.png", "ingameNavn": "it me sharp"}, {"navn": "Erixen", "id": "44513", "rolle": "mid", "spillerBilde": "https://img.gfx.no/2391/2391088/original.160x160c.jpg", "ingameNavn": "ERIX\u039eN"}, {"navn": "Chrisberg", "id": "92511", "rolle": "adc", "spillerBilde": "https://img.gfx.no/2604/2604473/picture.160x160c.png", "ingameNavn": "Johnny Dolphins"}, {"navn": "Touch", "id": "2474", "rolle": "sup", "spillerBilde": "https://img.gfx.no/2379/2379918/4iutuhze-400x400.160x160c.jpg", "ingameNavn": "Touch"}, {"navn": "", "id": "", "rolle": "chc", "spillerBilde": "", "ingameNavn": ""}]}}]