{"summonerName": "bj\u00f8rstar", "summonerId": "L7irim0WAKuiWU3q7GLOADma7wd18orJhneh6YN1s0Hgwg7a", "paradiseUserId": 100450, "mapsPlayed": 28, "playTime": "46222", "kills": 143, "deaths": 100, "assists": 154, "kadratio": "2.97", "killsPerMap": "5.11", "deathsPerMap": "3.57", "assistsPerMap": "5.50", "killsPerMinute": "0.19", "deathsPerMinute": "0.13", "assistsPerMinute": "0.20", "killParticipation": "60.12", "doubleKills": 17, "tripleKills": 2, "quadraKills": 0, "pentaKills": 0, "unrealKills": 0, "firstBloodKills": 3, "firstBloodAssists": 0, "firstTowerKills": 1, "firstTowerAssists": 1, "firstInhibitorKills": 6, "firstInhibitorAssist": 4, "totalMinionsKilled": 5343, "neutralMinionsKilled": 563, "neutralMinionsKilledTeamJungle": 364, "neutralMinionsKilledEnemyJungle": 58, "allMinionsKilled": 5906, "allMinionsKilledPerMinute": "7.67", "goldEarned": 313316, "goldSpent": 286083, "goldEarnedPerMinute": "406.71", "goldSpentPerMinute": "371.36", "visionScore": 496, "largestKillingSpree": 9, "largestMultiKill": 3, "totalDamageDealt": "3930402", "magicDamageDealt": "182549", "physicalDamageDealt": "3464889", "trueDamageDealt": "282945", "totalDamageDealtToChampions": "427333", "magicDamageDealtToChampions": 52541, "physicalDamageDealtToChampions": "333159", "trueDamageDealtToChampions": "41614", "totalDamageTaken": "382422", "magicalDamageTaken": "136773", "physicalDamageTaken": "233905", "trueDamageTaken": "11726", "totalDamagePerSecond": "85.03", "totalDamagePerMinute": "5101.99", "totalDamageToChampionsPerSecond": "9.25", "totalDamageToChampionsPerMinute": "554.71", "wardsPlaced": 199, "wardsKilled": 83, "controlWardsPurchased": 37, "paradiseSignupId": 171835, "user": {"id": 100450, "name": "bvikhagen", "steamId": null, "lolEuWestSummonerName": "bj\u00f8rstar", "pubgAccountName": null, "psnId": null, "url": "https://www.gamer.no/brukere/bvikhagen/100450", "image": "https://img.gfx.no/2573/2573550/last-ned.160x160c.jpg", "proImage": null, "cartoonImage": null, "country": {"id": 1, "name": "Norge", "nameEn": "Norway", "code": "NO"}, "accounts": [], "joinDate": "2020-05-18 10:20:40"}}