{"summonerName": "SW nQTerraz", "summonerId": "oVEwx1TL-c0pVudazCkbe4wS6Y0r9web7GvvkV9-vz2Bes2y", "paradiseUserId": 100782, "mapsPlayed": 30, "playTime": "51163", "kills": 143, "deaths": 73, "assists": 304, "kadratio": "6.12", "killsPerMap": "4.77", "deathsPerMap": "2.43", "assistsPerMap": "10.13", "killsPerMinute": "0.17", "deathsPerMinute": "0.09", "assistsPerMinute": "0.36", "killParticipation": "59.76", "doubleKills": 17, "tripleKills": 2, "quadraKills": 1, "pentaKills": 0, "unrealKills": 0, "firstBloodKills": 4, "firstBloodAssists": 0, "firstTowerKills": 3, "firstTowerAssists": 4, "firstInhibitorKills": 0, "firstInhibitorAssist": 11, "totalMinionsKilled": 788, "neutralMinionsKilled": 3765, "neutralMinionsKilledTeamJungle": 2349, "neutralMinionsKilledEnemyJungle": 468, "allMinionsKilled": 4553, "allMinionsKilledPerMinute": "5.34", "goldEarned": 314181, "goldSpent": 279840, "goldEarnedPerMinute": "368.45", "goldSpentPerMinute": "328.17", "visionScore": 996, "largestKillingSpree": 10, "largestMultiKill": 4, "totalDamageDealt": "4042690", "magicDamageDealt": "1861091", "physicalDamageDealt": "1871728", "trueDamageDealt": "309840", "totalDamageDealtToChampions": "340897", "magicDamageDealtToChampions": 184461, "physicalDamageDealtToChampions": "127068", "trueDamageDealtToChampions": "29337", "totalDamageTaken": "832548", "magicalDamageTaken": "268364", "physicalDamageTaken": "515430", "trueDamageTaken": "48729", "totalDamagePerSecond": "79.02", "totalDamagePerMinute": "4740.95", "totalDamageToChampionsPerSecond": "6.66", "totalDamageToChampionsPerMinute": "399.78", "wardsPlaced": 242, "wardsKilled": 221, "controlWardsPurchased": 216, "paradiseSignupId": 171229, "user": {"id": 100782, "name": "SW nQTerraz", "steamId": "1:0:57460654", "lolEuWestSummonerName": "SW nQTerraz", "pubgAccountName": null, "psnId": null, "url": "https://www.gamer.no/brukere/sw-nqterraz/100782", "image": "https://img.gfx.no/2574/2574854/capture-png-nq.160x160c.png", "proImage": null, "cartoonImage": null, "country": {"id": 1, "name": "Norge", "nameEn": "Norway", "code": "NO"}, "accounts": [], "joinDate": "2020-11-25 16:52:25"}}