{"summonerName": "GOD gripp", "summonerId": "10FM3z9RBB-Vp2Ysk2V02z0BAHT91CsoWceH25eKH_ExqjnL", "paradiseUserId": 101337, "mapsPlayed": 27, "playTime": "41922", "kills": 117, "deaths": 114, "assists": 212, "kadratio": "2.89", "killsPerMap": "4.33", "deathsPerMap": "4.22", "assistsPerMap": "7.85", "killsPerMinute": "0.17", "deathsPerMinute": "0.16", "assistsPerMinute": "0.30", "killParticipation": "59.17", "doubleKills": 10, "tripleKills": 1, "quadraKills": 0, "pentaKills": 0, "unrealKills": 0, "firstBloodKills": 7, "firstBloodAssists": 0, "firstTowerKills": 4, "firstTowerAssists": 5, "firstInhibitorKills": 5, "firstInhibitorAssist": 5, "totalMinionsKilled": 833, "neutralMinionsKilled": 2455, "neutralMinionsKilledTeamJungle": 1391, "neutralMinionsKilledEnemyJungle": 348, "allMinionsKilled": 3288, "allMinionsKilledPerMinute": "4.71", "goldEarned": 243614, "goldSpent": 226201, "goldEarnedPerMinute": "348.67", "goldSpentPerMinute": "323.75", "visionScore": 587, "largestKillingSpree": 8, "largestMultiKill": 3, "totalDamageDealt": "3185452", "magicDamageDealt": "913448", "physicalDamageDealt": "1889506", "trueDamageDealt": "382474", "totalDamageDealtToChampions": "273592", "magicDamageDealtToChampions": 70549, "physicalDamageDealtToChampions": "182963", "trueDamageDealtToChampions": "20062", "totalDamageTaken": "607366", "magicalDamageTaken": "169953", "physicalDamageTaken": "413961", "trueDamageTaken": "23434", "totalDamagePerSecond": "75.99", "totalDamagePerMinute": "4559.11", "totalDamageToChampionsPerSecond": "6.53", "totalDamageToChampionsPerMinute": "391.57", "wardsPlaced": 148, "wardsKilled": 91, "controlWardsPurchased": 79, "paradiseSignupId": 171863, "user": {"id": 101337, "name": "gripp", "steamId": null, "lolEuWestSummonerName": "GOD gripp", "pubgAccountName": null, "psnId": null, "url": "https://www.gamer.no/brukere/gripp/101337", "image": "https://img.gfx.no/1539/1539009/no-image.160x160c.png", "proImage": null, "cartoonImage": null, "country": {"id": 1, "name": "Norge", "nameEn": "Norway", "code": "NO"}, "accounts": [], "joinDate": "2020-07-30 20:53:44"}}