{"summonerName": "oai", "summonerId": "FauvG60t3MBu_ixscyT7O1gf80oJ_Nf-9vLdmYrQfdf5XQQ", "paradiseUserId": 101968, "mapsPlayed": 24, "playTime": "42800", "kills": 235, "deaths": 93, "assists": 222, "kadratio": "4.91", "killsPerMap": "9.79", "deathsPerMap": "3.88", "assistsPerMap": "9.25", "killsPerMinute": "0.33", "deathsPerMinute": "0.13", "assistsPerMinute": "0.31", "killParticipation": "64.28", "doubleKills": 37, "tripleKills": 7, "quadraKills": 0, "pentaKills": 0, "unrealKills": 0, "firstBloodKills": 4, "firstBloodAssists": 0, "firstTowerKills": 4, "firstTowerAssists": 2, "firstInhibitorKills": 3, "firstInhibitorAssist": 11, "totalMinionsKilled": 4518, "neutralMinionsKilled": 757, "neutralMinionsKilledTeamJungle": 365, "neutralMinionsKilledEnemyJungle": 195, "allMinionsKilled": 5275, "allMinionsKilledPerMinute": "7.39", "goldEarned": 331383, "goldSpent": 302944, "goldEarnedPerMinute": "464.56", "goldSpentPerMinute": "424.69", "visionScore": 660, "largestKillingSpree": 18, "largestMultiKill": 3, "totalDamageDealt": "4227045", "magicDamageDealt": "2297025", "physicalDamageDealt": "1762902", "trueDamageDealt": "167103", "totalDamageDealtToChampions": "619209", "magicDamageDealtToChampions": 387821, "physicalDamageDealtToChampions": "207053", "trueDamageDealtToChampions": "24318", "totalDamageTaken": "506850", "magicalDamageTaken": "185293", "physicalDamageTaken": "278932", "trueDamageTaken": "42606", "totalDamagePerSecond": "98.76", "totalDamagePerMinute": "5925.76", "totalDamageToChampionsPerSecond": "14.47", "totalDamageToChampionsPerMinute": "868.05", "wardsPlaced": 253, "wardsKilled": 96, "controlWardsPurchased": 78, "paradiseSignupId": 171941, "user": {"id": 101968, "name": "iT3chnoHD", "steamId": null, "lolEuWestSummonerName": "oai", "pubgAccountName": null, "psnId": null, "url": "https://www.gamer.no/brukere/it3chnohd/101968", "image": "https://img.gfx.no/2597/2597198/jirachi.160x160c.png", "proImage": null, "cartoonImage": null, "country": {"id": 1, "name": "Norge", "nameEn": "Norway", "code": "NO"}, "accounts": [], "joinDate": "2020-08-17 19:07:28"}}