{"summonerName": "weka1", "summonerId": "ku-nshlQD0I_x5pYxtBTJ_QtW64DTBexgyo4s9qS1SpsUSQ", "paradiseUserId": 102618, "mapsPlayed": 18, "playTime": "31701", "kills": 80, "deaths": 82, "assists": 63, "kadratio": "1.74", "killsPerMap": "4.44", "deathsPerMap": "4.56", "assistsPerMap": "3.50", "killsPerMinute": "0.15", "deathsPerMinute": "0.16", "assistsPerMinute": "0.12", "killParticipation": "54.37", "doubleKills": 12, "tripleKills": 1, "quadraKills": 0, "pentaKills": 0, "unrealKills": 0, "firstBloodKills": 0, "firstBloodAssists": 0, "firstTowerKills": 3, "firstTowerAssists": 1, "firstInhibitorKills": 3, "firstInhibitorAssist": 2, "totalMinionsKilled": 3937, "neutralMinionsKilled": 189, "neutralMinionsKilledTeamJungle": 72, "neutralMinionsKilledEnemyJungle": 54, "allMinionsKilled": 4126, "allMinionsKilledPerMinute": "7.81", "goldEarned": 220627, "goldSpent": 207774, "goldEarnedPerMinute": "417.58", "goldSpentPerMinute": "393.25", "visionScore": 480, "largestKillingSpree": 13, "largestMultiKill": 3, "totalDamageDealt": "2970344", "magicDamageDealt": "913209", "physicalDamageDealt": "1899341", "trueDamageDealt": "157784", "totalDamageDealtToChampions": "294209", "magicDamageDealtToChampions": 117612, "physicalDamageDealtToChampions": "162955", "trueDamageDealtToChampions": "13631", "totalDamageTaken": "352132", "magicalDamageTaken": "129074", "physicalDamageTaken": "204408", "trueDamageTaken": "18631", "totalDamagePerSecond": "93.70", "totalDamagePerMinute": "5621.92", "totalDamageToChampionsPerSecond": "9.28", "totalDamageToChampionsPerMinute": "556.84", "wardsPlaced": 210, "wardsKilled": 78, "controlWardsPurchased": 89, "paradiseSignupId": 153468, "user": {"id": 102618, "name": "weka", "steamId": null, "lolEuWestSummonerName": "weka1", "pubgAccountName": null, "psnId": null, "url": "https://www.gamer.no/brukere/weka/102618", "image": "https://img.gfx.no/1539/1539009/no-image.160x160c.png", "proImage": null, "cartoonImage": null, "country": {"id": 10, "name": "Finland", "nameEn": "Finland", "code": "FI"}, "accounts": [], "joinDate": "2021-03-23 17:03:37"}}