{"summonerName": "MetaChris", "summonerId": "00U08S1J8pkrCFmMaD-YHYNlw6zbkn5dSTMJdhYhHawJbVc", "paradiseUserId": 102855, "mapsPlayed": 8, "playTime": "13896", "kills": 22, "deaths": 43, "assists": 28, "kadratio": "1.16", "killsPerMap": "2.75", "deathsPerMap": "5.38", "assistsPerMap": "3.50", "killsPerMinute": "0.09", "deathsPerMinute": "0.19", "assistsPerMinute": "0.12", "killParticipation": "35.21", "doubleKills": 0, "tripleKills": 0, "quadraKills": 0, "pentaKills": 0, "unrealKills": 0, "firstBloodKills": 3, "firstBloodAssists": 0, "firstTowerKills": 0, "firstTowerAssists": 0, "firstInhibitorKills": 0, "firstInhibitorAssist": 0, "totalMinionsKilled": 1081, "neutralMinionsKilled": 26, "neutralMinionsKilledTeamJungle": 6, "neutralMinionsKilledEnemyJungle": 6, "allMinionsKilled": 1107, "allMinionsKilledPerMinute": "4.78", "goldEarned": 68961, "goldSpent": 66410, "goldEarnedPerMinute": "297.76", "goldSpentPerMinute": "286.74", "visionScore": 225, "largestKillingSpree": 3, "largestMultiKill": 1, "totalDamageDealt": "785259", "magicDamageDealt": "350440", "physicalDamageDealt": "358975", "trueDamageDealt": "75836", "totalDamageDealtToChampions": "114229", "magicDamageDealtToChampions": 67407, "physicalDamageDealtToChampions": "35834", "trueDamageDealtToChampions": "10985", "totalDamageTaken": "160041", "magicalDamageTaken": "57894", "physicalDamageTaken": "93644", "trueDamageTaken": "8500", "totalDamagePerSecond": "56.51", "totalDamagePerMinute": "3390.58", "totalDamageToChampionsPerSecond": "8.22", "totalDamageToChampionsPerMinute": "493.22", "wardsPlaced": 100, "wardsKilled": 35, "controlWardsPurchased": 22, "paradiseSignupId": 171921, "user": {"id": 102855, "name": "MetaChris", "steamId": null, "lolEuWestSummonerName": "MetaChris", "pubgAccountName": null, "psnId": null, "url": "https://www.gamer.no/brukere/metachris/102855", "image": "https://img.gfx.no/1539/1539009/no-image.160x160c.png", "proImage": null, "cartoonImage": null, "country": {"id": 1, "name": "Norge", "nameEn": "Norway", "code": "NO"}, "accounts": [], "joinDate": "2020-08-31 17:09:58"}}