{"summonerName": "glenniyaboy", "summonerId": "pnmYTOqVrJrdPbwy8SdKrN_Ya7zIqMgIzs0Q1hnRQnWrGHvg", "paradiseUserId": 102940, "mapsPlayed": 5, "playTime": "7564", "kills": 16, "deaths": 11, "assists": 45, "kadratio": "5.55", "killsPerMap": "3.20", "deathsPerMap": "2.20", "assistsPerMap": "9.00", "killsPerMinute": "0.13", "deathsPerMinute": "0.09", "assistsPerMinute": "0.36", "killParticipation": "39.61", "doubleKills": 2, "tripleKills": 0, "quadraKills": 0, "pentaKills": 0, "unrealKills": 0, "firstBloodKills": 0, "firstBloodAssists": 0, "firstTowerKills": 2, "firstTowerAssists": 1, "firstInhibitorKills": 1, "firstInhibitorAssist": 3, "totalMinionsKilled": 114, "neutralMinionsKilled": 578, "neutralMinionsKilledTeamJungle": 252, "neutralMinionsKilledEnemyJungle": 115, "allMinionsKilled": 692, "allMinionsKilledPerMinute": "5.49", "goldEarned": 47314, "goldSpent": 40660, "goldEarnedPerMinute": "375.31", "goldSpentPerMinute": "322.53", "visionScore": 93, "largestKillingSpree": 3, "largestMultiKill": 2, "totalDamageDealt": "644710", "magicDamageDealt": "239566", "physicalDamageDealt": "218336", "trueDamageDealt": "186802", "totalDamageDealtToChampions": "33338", "magicDamageDealtToChampions": 22652, "physicalDamageDealtToChampions": "9201", "trueDamageDealtToChampions": "1482", "totalDamageTaken": "126498", "magicalDamageTaken": "27113", "physicalDamageTaken": "96452", "trueDamageTaken": "2926", "totalDamagePerSecond": "85.23", "totalDamagePerMinute": "5114.04", "totalDamageToChampionsPerSecond": "4.41", "totalDamageToChampionsPerMinute": "264.45", "wardsPlaced": 20, "wardsKilled": 9, "controlWardsPurchased": 14, "paradiseSignupId": 171907, "user": {"id": 102940, "name": "GlenniYaBoy", "steamId": null, "lolEuWestSummonerName": "glenniyaboy", "pubgAccountName": null, "psnId": null, "url": "https://www.gamer.no/brukere/glenniyaboy/102940", "image": "https://img.gfx.no/1539/1539009/no-image.160x160c.png", "proImage": null, "cartoonImage": null, "country": {"id": 1, "name": "Norge", "nameEn": "Norway", "code": "NO"}, "accounts": [], "joinDate": "2020-09-03 09:40:23"}}