{"summonerName": "ssi paenti", "summonerId": "9sAJslZ45wzopUreQAX9rWFEZskMFiYLEDmLtRIURl6AQes", "paradiseUserId": 106304, "mapsPlayed": 10, "playTime": "18230", "kills": 36, "deaths": 17, "assists": 101, "kadratio": "8.06", "killsPerMap": "3.60", "deathsPerMap": "1.70", "assistsPerMap": "10.10", "killsPerMinute": "0.12", "deathsPerMinute": "0.06", "assistsPerMinute": "0.33", "killParticipation": "52.90", "doubleKills": 3, "tripleKills": 1, "quadraKills": 0, "pentaKills": 0, "unrealKills": 0, "firstBloodKills": 2, "firstBloodAssists": 0, "firstTowerKills": 1, "firstTowerAssists": 0, "firstInhibitorKills": 1, "firstInhibitorAssist": 2, "totalMinionsKilled": 1889, "neutralMinionsKilled": 39, "neutralMinionsKilledTeamJungle": 0, "neutralMinionsKilledEnemyJungle": 28, "allMinionsKilled": 1928, "allMinionsKilledPerMinute": "6.35", "goldEarned": 112945, "goldSpent": 102905, "goldEarnedPerMinute": "371.73", "goldSpentPerMinute": "338.69", "visionScore": 184, "largestKillingSpree": 9, "largestMultiKill": 3, "totalDamageDealt": "1224821", "magicDamageDealt": "565994", "physicalDamageDealt": "518565", "trueDamageDealt": "140254", "totalDamageDealtToChampions": "136850", "magicDamageDealtToChampions": 71661, "physicalDamageDealtToChampions": "61552", "trueDamageDealtToChampions": "3628", "totalDamageTaken": "173939", "magicalDamageTaken": "61438", "physicalDamageTaken": "104514", "trueDamageTaken": "7977", "totalDamagePerSecond": "67.19", "totalDamagePerMinute": "4031.23", "totalDamageToChampionsPerSecond": "7.51", "totalDamageToChampionsPerMinute": "450.41", "wardsPlaced": 85, "wardsKilled": 19, "controlWardsPurchased": 23, "paradiseSignupId": 172618, "user": {"id": 106304, "name": "JimmyHoang", "steamId": null, "lolEuWestSummonerName": "ssi paenti", "pubgAccountName": null, "psnId": null, "url": "https://www.gamer.no/brukere/jimmyhoang/106304", "image": "https://img.gfx.no/1539/1539009/no-image.160x160c.png", "proImage": null, "cartoonImage": null, "country": {"id": 1, "name": "Norge", "nameEn": "Norway", "code": "NO"}, "accounts": [], "joinDate": "2021-01-06 16:19:22"}}