{"summonerName": "Cowspace200", "summonerId": "Zyb7Xv67W4lU41kkHlIo9lg1_8J7_FLeMl2tLvweNDSrXAg", "paradiseUserId": 106682, "mapsPlayed": 6, "playTime": "10243", "kills": 25, "deaths": 29, "assists": 45, "kadratio": "2.41", "killsPerMap": "4.17", "deathsPerMap": "4.83", "assistsPerMap": "7.50", "killsPerMinute": "0.15", "deathsPerMinute": "0.17", "assistsPerMinute": "0.26", "killParticipation": "46.05", "doubleKills": 1, "tripleKills": 0, "quadraKills": 0, "pentaKills": 0, "unrealKills": 0, "firstBloodKills": 0, "firstBloodAssists": 0, "firstTowerKills": 2, "firstTowerAssists": 0, "firstInhibitorKills": 1, "firstInhibitorAssist": 2, "totalMinionsKilled": 662, "neutralMinionsKilled": 463, "neutralMinionsKilledTeamJungle": 289, "neutralMinionsKilledEnemyJungle": 24, "allMinionsKilled": 1125, "allMinionsKilledPerMinute": "6.59", "goldEarned": 67284, "goldSpent": 60020, "goldEarnedPerMinute": "394.13", "goldSpentPerMinute": "351.58", "visionScore": 184, "largestKillingSpree": 7, "largestMultiKill": 2, "totalDamageDealt": "947224", "magicDamageDealt": "518549", "physicalDamageDealt": "164921", "trueDamageDealt": "263747", "totalDamageDealtToChampions": "72230", "magicDamageDealtToChampions": 52629, "physicalDamageDealtToChampions": "6123", "trueDamageDealtToChampions": "13474", "totalDamageTaken": "192054", "magicalDamageTaken": "60518", "physicalDamageTaken": "117631", "trueDamageTaken": "13899", "totalDamagePerSecond": "92.48", "totalDamagePerMinute": "5548.52", "totalDamageToChampionsPerSecond": "7.05", "totalDamageToChampionsPerMinute": "423.10", "wardsPlaced": 67, "wardsKilled": 18, "controlWardsPurchased": 30, "paradiseSignupId": 173549, "user": {"id": 106682, "name": "Cowspace", "steamId": null, "lolEuWestSummonerName": "Cowspace200", "pubgAccountName": null, "psnId": null, "url": "https://www.gamer.no/brukere/cowspace/106682", "image": "https://img.gfx.no/2641/2641653/jostein-crab.160x160c.png", "proImage": null, "cartoonImage": null, "country": {"id": 1, "name": "Norge", "nameEn": "Norway", "code": "NO"}, "accounts": [], "joinDate": "2021-01-13 19:21:54"}}