{"summonerName": "Ragney", "summonerId": "w0SqTBKMLb1Ak_iYdRg9Te5ptmuMys9XR7rbp4FZwFSipRk", "paradiseUserId": 106765, "mapsPlayed": 14, "playTime": "23921", "kills": 21, "deaths": 59, "assists": 32, "kadratio": "0.90", "killsPerMap": "1.50", "deathsPerMap": "4.21", "assistsPerMap": "2.29", "killsPerMinute": "0.05", "deathsPerMinute": "0.15", "assistsPerMinute": "0.08", "killParticipation": "31.74", "doubleKills": 2, "tripleKills": 1, "quadraKills": 0, "pentaKills": 0, "unrealKills": 0, "firstBloodKills": 0, "firstBloodAssists": 0, "firstTowerKills": 0, "firstTowerAssists": 0, "firstInhibitorKills": 1, "firstInhibitorAssist": 0, "totalMinionsKilled": 2202, "neutralMinionsKilled": 12, "neutralMinionsKilledTeamJungle": 4, "neutralMinionsKilledEnemyJungle": 0, "allMinionsKilled": 2214, "allMinionsKilledPerMinute": "5.55", "goldEarned": 118757, "goldSpent": 109675, "goldEarnedPerMinute": "297.87", "goldSpentPerMinute": "275.09", "visionScore": 319, "largestKillingSpree": 4, "largestMultiKill": 3, "totalDamageDealt": "1610724", "magicDamageDealt": "147403", "physicalDamageDealt": "1384929", "trueDamageDealt": "78384", "totalDamageDealtToChampions": "123961", "magicDamageDealtToChampions": 22132, "physicalDamageDealtToChampions": "100061", "trueDamageDealtToChampions": "1758", "totalDamageTaken": "271968", "magicalDamageTaken": "95748", "physicalDamageTaken": "162832", "trueDamageTaken": "13374", "totalDamagePerSecond": "67.34", "totalDamagePerMinute": "4040.11", "totalDamageToChampionsPerSecond": "5.18", "totalDamageToChampionsPerMinute": "310.93", "wardsPlaced": 138, "wardsKilled": 38, "controlWardsPurchased": 56, "paradiseSignupId": 173566, "user": {"id": 106765, "name": "Ragney", "steamId": null, "lolEuWestSummonerName": "Ragney", "pubgAccountName": null, "psnId": null, "url": "https://www.gamer.no/brukere/ragney/106765", "image": "https://img.gfx.no/1539/1539009/no-image.160x160c.png", "proImage": null, "cartoonImage": null, "country": {"id": 1, "name": "Norge", "nameEn": "Norway", "code": "NO"}, "accounts": [], "joinDate": "2021-01-14 20:02:27"}}