{"summonerName": "YEHA", "summonerId": "gZszc52387S3YCFt_NMhSKWbItWwgvhT0TQss9qB4eh0eWo", "paradiseUserId": 3075, "mapsPlayed": 8, "playTime": "12079", "kills": 57, "deaths": 33, "assists": 77, "kadratio": "4.06", "killsPerMap": "7.13", "deathsPerMap": "4.13", "assistsPerMap": "9.63", "killsPerMinute": "0.28", "deathsPerMinute": "0.16", "assistsPerMinute": "0.38", "killParticipation": "47.52", "doubleKills": 5, "tripleKills": 2, "quadraKills": 1, "pentaKills": 1, "unrealKills": 0, "firstBloodKills": 0, "firstBloodAssists": 0, "firstTowerKills": 0, "firstTowerAssists": 0, "firstInhibitorKills": 0, "firstInhibitorAssist": 2, "totalMinionsKilled": 180, "neutralMinionsKilled": 832, "neutralMinionsKilledTeamJungle": 483, "neutralMinionsKilledEnemyJungle": 109, "allMinionsKilled": 1012, "allMinionsKilledPerMinute": "5.03", "goldEarned": 80323, "goldSpent": 67395, "goldEarnedPerMinute": "398.99", "goldSpentPerMinute": "334.77", "visionScore": 148, "largestKillingSpree": 5, "largestMultiKill": 5, "totalDamageDealt": "923813", "magicDamageDealt": "334601", "physicalDamageDealt": "485600", "trueDamageDealt": "103607", "totalDamageDealtToChampions": "103274", "magicDamageDealtToChampions": 29270, "physicalDamageDealtToChampions": "66389", "trueDamageDealtToChampions": "7611", "totalDamageTaken": "214770", "magicalDamageTaken": "62486", "physicalDamageTaken": "143454", "trueDamageTaken": "8822", "totalDamagePerSecond": "76.48", "totalDamagePerMinute": "4588.86", "totalDamageToChampionsPerSecond": "8.55", "totalDamageToChampionsPerMinute": "512.99", "wardsPlaced": 65, "wardsKilled": 17, "controlWardsPurchased": 36, "paradiseSignupId": 172602, "user": {"id": 3075, "name": "FARLIG SPILLER", "steamId": "0:1:48359615", "lolEuWestSummonerName": "YEHA", "pubgAccountName": null, "psnId": "", "url": "https://www.gamer.no/brukere/farlig-spiller/3075", "image": "https://img.gfx.no/2566/2566473/fdfdfdfd.160x160c.png", "proImage": null, "cartoonImage": null, "country": {"id": 1, "name": "Norge", "nameEn": "Norway", "code": "NO"}, "accounts": [{"nickname": "GucciGaze", "remoteUserId": "fa65d941-b952-4f2c-85b4-16979f36907e", "url": "https://www.faceit.com/en/players/GucciGaze", "system": {"name": "FACEIT", "url": "https://www.faceit.com"}}], "joinDate": "2021-01-07 01:54:46"}}