{"summonerName": "Alexkazam", "summonerId": "zePVIEhUvYPxcPLeIY_t1jfneT9Qdjt2UEaqZ9M9f8aA2cs", "paradiseUserId": 42692, "mapsPlayed": 12, "playTime": "23787", "kills": 57, "deaths": 40, "assists": 122, "kadratio": "4.48", "killsPerMap": "4.75", "deathsPerMap": "3.33", "assistsPerMap": "10.17", "killsPerMinute": "0.14", "deathsPerMinute": "0.10", "assistsPerMinute": "0.31", "killParticipation": "58.50", "doubleKills": 4, "tripleKills": 0, "quadraKills": 0, "pentaKills": 0, "unrealKills": 0, "firstBloodKills": 1, "firstBloodAssists": 0, "firstTowerKills": 2, "firstTowerAssists": 1, "firstInhibitorKills": 1, "firstInhibitorAssist": 4, "totalMinionsKilled": 2415, "neutralMinionsKilled": 106, "neutralMinionsKilledTeamJungle": 62, "neutralMinionsKilledEnemyJungle": 18, "allMinionsKilled": 2521, "allMinionsKilledPerMinute": "6.36", "goldEarned": 146349, "goldSpent": 132525, "goldEarnedPerMinute": "369.15", "goldSpentPerMinute": "334.28", "visionScore": 314, "largestKillingSpree": 6, "largestMultiKill": 2, "totalDamageDealt": "1735482", "magicDamageDealt": "1311719", "physicalDamageDealt": "385305", "trueDamageDealt": "38452", "totalDamageDealtToChampions": "224129", "magicDamageDealtToChampions": 198419, "physicalDamageDealtToChampions": "22150", "trueDamageDealtToChampions": "3553", "totalDamageTaken": "154496", "magicalDamageTaken": "60479", "physicalDamageTaken": "86809", "trueDamageTaken": "7198", "totalDamagePerSecond": "72.96", "totalDamagePerMinute": "4377.56", "totalDamageToChampionsPerSecond": "9.42", "totalDamageToChampionsPerMinute": "565.34", "wardsPlaced": 137, "wardsKilled": 36, "controlWardsPurchased": 53, "paradiseSignupId": 173640, "user": {"id": 42692, "name": "AlexanderBerg00", "steamId": "1:0:78903814", "lolEuWestSummonerName": "Alexkazam", "pubgAccountName": null, "psnId": null, "url": "https://www.gamer.no/brukere/alexanderberg00/42692", "image": "https://img.gfx.no/1539/1539009/no-image.160x160c.png", "proImage": null, "cartoonImage": null, "country": {"id": 1, "name": "Norge", "nameEn": "Norway", "code": "NO"}, "accounts": [{"nickname": "MarcusSilent", "remoteUserId": "db39876a-150d-45bd-8fde-567827647097", "url": "https://www.faceit.com/en/players/MarcusSilent", "system": {"name": "FACEIT", "url": "https://www.faceit.com"}}], "joinDate": "2021-01-20 18:08:08"}}