{"summonerName": "DragonShrek", "summonerId": "2sTPFcNZEPIzOy796dbIjGGFaKtm6M0tUTMIco7s6cRF4Q4", "paradiseUserId": 45387, "mapsPlayed": 69, "playTime": "119428", "kills": 279, "deaths": 274, "assists": 447, "kadratio": "2.65", "killsPerMap": "4.04", "deathsPerMap": "3.97", "assistsPerMap": "6.48", "killsPerMinute": "0.14", "deathsPerMinute": "0.14", "assistsPerMinute": "0.22", "killParticipation": "49.29", "doubleKills": 25, "tripleKills": 3, "quadraKills": 1, "pentaKills": 0, "unrealKills": 0, "firstBloodKills": 6, "firstBloodAssists": 0, "firstTowerKills": 8, "firstTowerAssists": 4, "firstInhibitorKills": 6, "firstInhibitorAssist": 10, "totalMinionsKilled": 12943, "neutralMinionsKilled": 869, "neutralMinionsKilledTeamJungle": 344, "neutralMinionsKilledEnemyJungle": 279, "allMinionsKilled": 13812, "allMinionsKilledPerMinute": "6.94", "goldEarned": 779807, "goldSpent": 725844, "goldEarnedPerMinute": "391.77", "goldSpentPerMinute": "364.66", "visionScore": 1900, "largestKillingSpree": 9, "largestMultiKill": 4, "totalDamageDealt": "10185512", "magicDamageDealt": "3830650", "physicalDamageDealt": "5811187", "trueDamageDealt": "543613", "totalDamageDealtToChampions": "1162839", "magicDamageDealtToChampions": 514668, "physicalDamageDealtToChampions": "609530", "trueDamageDealtToChampions": "38597", "totalDamageTaken": "1495107", "magicalDamageTaken": "490001", "physicalDamageTaken": "900945", "trueDamageTaken": "104100", "totalDamagePerSecond": "85.29", "totalDamagePerMinute": "5117.15", "totalDamageToChampionsPerSecond": "9.74", "totalDamageToChampionsPerMinute": "584.20", "wardsPlaced": 952, "wardsKilled": 210, "controlWardsPurchased": 339, "paradiseSignupId": 171905, "user": {"id": 45387, "name": "DragonShrek", "steamId": null, "lolEuWestSummonerName": "DragonShrek", "pubgAccountName": null, "psnId": null, "url": "https://www.gamer.no/brukere/dragonshrek/45387", "image": "https://img.gfx.no/2391/2391514/pb-gamer.160x160c.jpg", "proImage": null, "cartoonImage": null, "country": {"id": 1, "name": "Norge", "nameEn": "Norway", "code": "NO"}, "accounts": [], "joinDate": "2020-08-26 22:15:58"}}