{"summonerName": "Danjol123", "summonerId": "pOA_OmlTo4SBSmBMxNqqpBXgzFb5lB5DY7hTJ_G-auQH7bww", "paradiseUserId": 60436, "mapsPlayed": 42, "playTime": "71546", "kills": 180, "deaths": 209, "assists": 261, "kadratio": "2.11", "killsPerMap": "4.29", "deathsPerMap": "4.98", "assistsPerMap": "6.21", "killsPerMinute": "0.15", "deathsPerMinute": "0.18", "assistsPerMinute": "0.22", "killParticipation": "53.39", "doubleKills": 25, "tripleKills": 5, "quadraKills": 2, "pentaKills": 1, "unrealKills": 0, "firstBloodKills": 5, "firstBloodAssists": 0, "firstTowerKills": 2, "firstTowerAssists": 4, "firstInhibitorKills": 3, "firstInhibitorAssist": 7, "totalMinionsKilled": 5474, "neutralMinionsKilled": 514, "neutralMinionsKilledTeamJungle": 280, "neutralMinionsKilledEnemyJungle": 52, "allMinionsKilled": 5988, "allMinionsKilledPerMinute": "5.02", "goldEarned": 401382, "goldSpent": 360564, "goldEarnedPerMinute": "336.61", "goldSpentPerMinute": "302.38", "visionScore": 710, "largestKillingSpree": 10, "largestMultiKill": 5, "totalDamageDealt": "4098594", "magicDamageDealt": "640233", "physicalDamageDealt": "3144826", "trueDamageDealt": "313509", "totalDamageDealtToChampions": "567647", "magicDamageDealtToChampions": 176280, "physicalDamageDealtToChampions": "365652", "trueDamageDealtToChampions": "25687", "totalDamageTaken": "576590", "magicalDamageTaken": "207902", "physicalDamageTaken": "338520", "trueDamageTaken": "30128", "totalDamagePerSecond": "57.29", "totalDamagePerMinute": "3437.17", "totalDamageToChampionsPerSecond": "7.93", "totalDamageToChampionsPerMinute": "476.04", "wardsPlaced": 311, "wardsKilled": 98, "controlWardsPurchased": 52, "paradiseSignupId": 171581, "user": {"id": 60436, "name": "Danjol", "steamId": "1:1:124788060", "lolEuWestSummonerName": "Danjol123", "pubgAccountName": null, "psnId": null, "url": "https://www.gamer.no/brukere/danjol/60436", "image": "https://img.gfx.no/2078/2078912/tumblr-static-bdkwm6553aos44k000so80g8k.160x160c.png", "proImage": {"original": {"url": "https://img.gfx.no/2078/2078912/tumblr-static-bdkwm6553aos44k000so80g8k.png", "width": 500, "height": 462, "ratio": 1.08225}, "small": {"width": 400, "height": 370, "ratio": "1.08225", "url": "https://img.gfx.no/2078/2078912/tumblr-static-bdkwm6553aos44k000so80g8k.400x370.png"}, "cropped": {"width": 400, "height": 400, "ratio": 1, "url": "https://img.gfx.no/2078/2078912/tumblr-static-bdkwm6553aos44k000so80g8k.400x400c.png"}}, "cartoonImage": null, "country": {"id": 1, "name": "Norge", "nameEn": "Norway", "code": "NO"}, "accounts": [{"nickname": "EkteRotteN", "remoteUserId": "90847ea9-b14c-435f-adc6-d1d84880e944", "url": "https://www.faceit.com/en/players/EkteRotteN", "system": {"name": "FACEIT", "url": "https://www.faceit.com"}}], "joinDate": "2020-01-15 09:43:48"}}