{"summonerName": "BakaForLife", "summonerId": "jh3srSaWFrgBRee8W0qcyDPIU5diAfs-WBxMriKh0Q-FsHk", "paradiseUserId": 67534, "mapsPlayed": 76, "playTime": "134822", "kills": 354, "deaths": 340, "assists": 445, "kadratio": "2.35", "killsPerMap": "4.66", "deathsPerMap": "4.47", "assistsPerMap": "5.86", "killsPerMinute": "0.16", "deathsPerMinute": "0.15", "assistsPerMinute": "0.20", "killParticipation": "48.84", "doubleKills": 36, "tripleKills": 2, "quadraKills": 0, "pentaKills": 0, "unrealKills": 0, "firstBloodKills": 12, "firstBloodAssists": 0, "firstTowerKills": 11, "firstTowerAssists": 2, "firstInhibitorKills": 7, "firstInhibitorAssist": 7, "totalMinionsKilled": 14021, "neutralMinionsKilled": 560, "neutralMinionsKilledTeamJungle": 253, "neutralMinionsKilledEnemyJungle": 147, "allMinionsKilled": 14581, "allMinionsKilledPerMinute": "6.49", "goldEarned": 846895, "goldSpent": 798622, "goldEarnedPerMinute": "376.89", "goldSpentPerMinute": "355.41", "visionScore": 1365, "largestKillingSpree": 10, "largestMultiKill": 3, "totalDamageDealt": "10023508", "magicDamageDealt": "2522743", "physicalDamageDealt": "6967793", "trueDamageDealt": "532908", "totalDamageDealtToChampions": "1324527", "magicDamageDealtToChampions": 431173, "physicalDamageDealtToChampions": "804349", "trueDamageDealtToChampions": "88946", "totalDamageTaken": "1726879", "magicalDamageTaken": "586052", "physicalDamageTaken": "1037896", "trueDamageTaken": "102868", "totalDamagePerSecond": "74.35", "totalDamagePerMinute": "4460.77", "totalDamageToChampionsPerSecond": "9.82", "totalDamageToChampionsPerMinute": "589.46", "wardsPlaced": 643, "wardsKilled": 166, "controlWardsPurchased": 58, "paradiseSignupId": 171551, "user": {"id": 67534, "name": "BakaForLife", "steamId": null, "lolEuWestSummonerName": "BakaForLife", "pubgAccountName": null, "psnId": null, "url": "https://www.gamer.no/brukere/bakaforlife/67534", "image": "https://img.gfx.no/1539/1539009/no-image.160x160c.png", "proImage": null, "cartoonImage": null, "country": {"id": 1, "name": "Norge", "nameEn": "Norway", "code": "NO"}, "accounts": [], "joinDate": "2019-01-16 19:55:50"}}