{"summonerName": "Ils\u00e9th", "summonerId": "pfREqO4hZIX41MOmgXdIrNlq6VYo4b1l_Q_1eflZJjVwrmw", "paradiseUserId": 82892, "mapsPlayed": 10, "playTime": "16515", "kills": 44, "deaths": 38, "assists": 63, "kadratio": "2.82", "killsPerMap": "4.40", "deathsPerMap": "3.80", "assistsPerMap": "6.30", "killsPerMinute": "0.16", "deathsPerMinute": "0.14", "assistsPerMinute": "0.23", "killParticipation": "59.12", "doubleKills": 6, "tripleKills": 1, "quadraKills": 0, "pentaKills": 0, "unrealKills": 0, "firstBloodKills": 1, "firstBloodAssists": 0, "firstTowerKills": 1, "firstTowerAssists": 0, "firstInhibitorKills": 2, "firstInhibitorAssist": 2, "totalMinionsKilled": 253, "neutralMinionsKilled": 1400, "neutralMinionsKilledTeamJungle": 1000, "neutralMinionsKilledEnemyJungle": 42, "allMinionsKilled": 1653, "allMinionsKilledPerMinute": "6.01", "goldEarned": 101496, "goldSpent": 89608, "goldEarnedPerMinute": "368.74", "goldSpentPerMinute": "325.55", "visionScore": 290, "largestKillingSpree": 8, "largestMultiKill": 3, "totalDamageDealt": "1479885", "magicDamageDealt": "453911", "physicalDamageDealt": "912465", "trueDamageDealt": "113499", "totalDamageDealtToChampions": "118418", "magicDamageDealtToChampions": 35821, "physicalDamageDealtToChampions": "74790", "trueDamageDealtToChampions": "7799", "totalDamageTaken": "250345", "magicalDamageTaken": "63649", "physicalDamageTaken": "174654", "trueDamageTaken": "12034", "totalDamagePerSecond": "89.61", "totalDamagePerMinute": "5376.51", "totalDamageToChampionsPerSecond": "7.17", "totalDamageToChampionsPerMinute": "430.22", "wardsPlaced": 35, "wardsKilled": 63, "controlWardsPurchased": 35, "paradiseSignupId": 173033, "user": {"id": 82892, "name": "kridah98", "steamId": null, "lolEuWestSummonerName": "Ils\u00e9th", "pubgAccountName": null, "psnId": null, "url": "https://www.gamer.no/brukere/kridah98/82892", "image": "https://img.gfx.no/1539/1539009/no-image.160x160c.png", "proImage": null, "cartoonImage": null, "country": {"id": 1, "name": "Norge", "nameEn": "Norway", "code": "NO"}, "accounts": [], "joinDate": "2020-10-20 16:05:44"}}