{"summonerName": "Good Memes", "summonerId": "hjl56yaXCpcmN6XY4f2EZytcxHqRegw_lmNuLwxNrCD-u9g", "paradiseUserId": 87517, "mapsPlayed": 26, "playTime": "44408", "kills": 130, "deaths": 114, "assists": 211, "kadratio": "2.99", "killsPerMap": "5.00", "deathsPerMap": "4.38", "assistsPerMap": "8.12", "killsPerMinute": "0.18", "deathsPerMinute": "0.15", "assistsPerMinute": "0.29", "killParticipation": "61.66", "doubleKills": 17, "tripleKills": 3, "quadraKills": 1, "pentaKills": 0, "unrealKills": 0, "firstBloodKills": 2, "firstBloodAssists": 0, "firstTowerKills": 0, "firstTowerAssists": 2, "firstInhibitorKills": 5, "firstInhibitorAssist": 4, "totalMinionsKilled": 4184, "neutralMinionsKilled": 246, "neutralMinionsKilledTeamJungle": 99, "neutralMinionsKilledEnemyJungle": 33, "allMinionsKilled": 4430, "allMinionsKilledPerMinute": "5.99", "goldEarned": 287945, "goldSpent": 257825, "goldEarnedPerMinute": "389.04", "goldSpentPerMinute": "348.35", "visionScore": 506, "largestKillingSpree": 6, "largestMultiKill": 4, "totalDamageDealt": "3012964", "magicDamageDealt": "341138", "physicalDamageDealt": "2508519", "trueDamageDealt": "163293", "totalDamageDealtToChampions": "382844", "magicDamageDealtToChampions": 84469, "physicalDamageDealtToChampions": "284391", "trueDamageDealtToChampions": "13964", "totalDamageTaken": "390404", "magicalDamageTaken": "148290", "physicalDamageTaken": "227235", "trueDamageTaken": "14864", "totalDamagePerSecond": "67.85", "totalDamagePerMinute": "4070.84", "totalDamageToChampionsPerSecond": "8.62", "totalDamageToChampionsPerMinute": "517.26", "wardsPlaced": 230, "wardsKilled": 72, "controlWardsPurchased": 62, "paradiseSignupId": 171895, "user": {"id": 87517, "name": "Crizpy_kZ", "steamId": null, "lolEuWestSummonerName": "Good Memes", "pubgAccountName": null, "psnId": null, "url": "https://www.gamer.no/brukere/crizpy-kz/87517", "image": "https://img.gfx.no/2467/2467206/3vvtpbn.160x160c.png", "proImage": null, "cartoonImage": null, "country": {"id": 1, "name": "Norge", "nameEn": "Norway", "code": "NO"}, "accounts": [], "joinDate": "2019-08-14 19:35:55"}}