{"summonerName": "Supertrick", "summonerId": "lELhqx3NptSw0bjxltaNtgXzebFzIsXn1o62t4HZ1u6wFtM", "paradiseUserId": 98741, "mapsPlayed": 11, "playTime": "17741", "kills": 42, "deaths": 22, "assists": 73, "kadratio": "5.23", "killsPerMap": "3.82", "deathsPerMap": "2.00", "assistsPerMap": "6.64", "killsPerMinute": "0.14", "deathsPerMinute": "0.07", "assistsPerMinute": "0.25", "killParticipation": "42.91", "doubleKills": 6, "tripleKills": 0, "quadraKills": 0, "pentaKills": 0, "unrealKills": 0, "firstBloodKills": 2, "firstBloodAssists": 0, "firstTowerKills": 1, "firstTowerAssists": 1, "firstInhibitorKills": 1, "firstInhibitorAssist": 4, "totalMinionsKilled": 1932, "neutralMinionsKilled": 142, "neutralMinionsKilledTeamJungle": 57, "neutralMinionsKilledEnemyJungle": 33, "allMinionsKilled": 2074, "allMinionsKilledPerMinute": "7.01", "goldEarned": 114792, "goldSpent": 112795, "goldEarnedPerMinute": "388.23", "goldSpentPerMinute": "381.47", "visionScore": 301, "largestKillingSpree": 9, "largestMultiKill": 2, "totalDamageDealt": "1354695", "magicDamageDealt": "209648", "physicalDamageDealt": "1062548", "trueDamageDealt": "82491", "totalDamageDealtToChampions": "141803", "magicDamageDealtToChampions": 25694, "physicalDamageDealtToChampions": "106302", "trueDamageDealtToChampions": "9802", "totalDamageTaken": "210438", "magicalDamageTaken": "72099", "physicalDamageTaken": "129418", "trueDamageTaken": "8912", "totalDamagePerSecond": "76.36", "totalDamagePerMinute": "4581.57", "totalDamageToChampionsPerSecond": "7.99", "totalDamageToChampionsPerMinute": "479.58", "wardsPlaced": 115, "wardsKilled": 31, "controlWardsPurchased": 37, "paradiseSignupId": 173078, "user": {"id": 98741, "name": "Supertrick", "steamId": null, "lolEuWestSummonerName": "Supertrick", "pubgAccountName": null, "psnId": null, "url": "https://www.gamer.no/brukere/supertrick/98741", "image": "https://img.gfx.no/2650/2650573/bumblebee3-jumbo-v2.160x160c.jpg", "proImage": null, "cartoonImage": null, "country": {"id": 1, "name": "Norge", "nameEn": "Norway", "code": "NO"}, "accounts": [], "joinDate": "2021-01-14 18:43:40"}}